homegrid/__init__.py
homegrid/assets/bins/compost_bin.png
homegrid/assets/bins/compost_bin_closed.png
homegrid/assets/bins/compost_bin_open.png
homegrid/assets/bins/recycling_bin.png
homegrid/assets/bins/recycling_bin_closed.png
homegrid/assets/bins/recycling_bin_open.png
homegrid/assets/bins/trash_bin.png
homegrid/assets/bins/trash_bin_closed.png
homegrid/assets/bins/trash_bin_open.png
homegrid/assets/cabinet.png
homegrid/assets/carpet.png
homegrid/assets/chair.png
homegrid/assets/chairl.png
homegrid/assets/chairr.png
homegrid/assets/coffeetable.png
homegrid/assets/countertop.png
homegrid/assets/cupboard.png
homegrid/assets/egg_0.png
homegrid/assets/egg_1.png
homegrid/assets/egg_2.png
homegrid/assets/egg_3.png
homegrid/assets/fridge.png
homegrid/assets/lamp.png
homegrid/assets/objects/bottle.png
homegrid/assets/objects/fruit.png
homegrid/assets/objects/papers.png
homegrid/assets/objects/plates.png
homegrid/assets/plant.png
homegrid/assets/robot.png
homegrid/assets/rugl.png
homegrid/assets/rugr.png
homegrid/assets/sofa.png
homegrid/assets/sofa_side.png
homegrid/assets/stove.png
homegrid/assets/table.png
homegrid/assets/tile.png
homegrid/assets/tomato_0.png
homegrid/assets/tomato_1.png
homegrid/assets/tomato_2.png
homegrid/assets/wood.png
homegrid/base.py
homegrid/benchmark.py
homegrid/homegrid_base.py
homegrid/homegrid_embeds.pkl
homegrid/homegrid_sentences.txt
homegrid/language_wrappers.py
homegrid/layout.py
homegrid/manual_control.py
homegrid/rendering.py
homegrid/window.py
homegrid/wrappers.py
homegrid-0.1.1.dist-info/LICENSE
homegrid-0.1.1.dist-info/METADATA
homegrid-0.1.1.dist-info/WHEEL
homegrid-0.1.1.dist-info/RECORD
