Metadata-Version: 2.1
Name: homegrid
Version: 0.1.1
Summary: A minimal home gridworld environment to test how agents use language hints.
Keywords: environment,agent,rl,language
Author: Jessy Lin
Author-email: jessy81697@gmail.com
Requires-Python: >=3.8,<4.0
Classifier: Programming Language :: Python :: 3
Classifier: Programming Language :: Python :: 3.8
Classifier: Programming Language :: Python :: 3.9
Classifier: Programming Language :: Python :: 3.10
Classifier: Programming Language :: Python :: 3.11
Provides-Extra: dev
Requires-Dist: gym (==0.26)
Requires-Dist: matplotlib
Requires-Dist: numpy
Requires-Dist: sentencepiece
Requires-Dist: tokenizers
Requires-Dist: torch ; extra == "dev"
Requires-Dist: transformers ; extra == "dev"
